physioex/__init__.py
physioex/data/__init__.py
physioex/data/datamodule.py
physioex/data/datareader.py
physioex/data/dataset.py
physioex/explain/__init__.py
physioex/preprocess/__init__.py
physioex/preprocess/dcsm.py
physioex/preprocess/hmc.py
physioex/preprocess/hpap.py
physioex/preprocess/kornum.py
physioex/preprocess/mass.py
physioex/preprocess/mesa.py
physioex/preprocess/mros.py
physioex/preprocess/preprocessor.py
physioex/preprocess/shhs.py
physioex/preprocess/sleepedf.py
physioex/preprocess/wsc.py
physioex/preprocess/bin/compress_datasets.py
physioex/preprocess/bin/main.py
physioex/preprocess/utils/mousedata.py
physioex/preprocess/utils/signal.py
physioex/preprocess/utils/sleepdata.py
physioex/train/__init__.py
physioex/train/bin/__init__.py
physioex/train/bin/dist_train.py
physioex/train/bin/finetune.py
physioex/train/bin/parser.py
physioex/train/bin/test.py
physioex/train/bin/train.py
physioex/train/models/__init__.py
physioex/train/models/check_table.csv
physioex/train/models/load.py
physioex/train/networks/__init__.py
physioex/train/networks/base.py
physioex/train/networks/chambon2018.py
physioex/train/networks/config.yaml
physioex/train/networks/prototype.py
physioex/train/networks/seqsexnet.py
physioex/train/networks/seqsleepnet.py
physioex/train/networks/sleeptransformer.py
physioex/train/networks/tinysleepnet.py
physioex/train/networks/utils/layers.py
physioex/train/networks/utils/loss.py
physioex/train/networks/utils/target_transform.py
physioex/train/utils/__init__.py
physioex/train/utils/finetune.py
physioex/train/utils/test.py
physioex/train/utils/train.py
physioex-1.0.8.dist-info/licenses/LICENSE
physioex-1.0.8.dist-info/METADATA
physioex-1.0.8.dist-info/WHEEL
physioex-1.0.8.dist-info/entry_points.txt
physioex-1.0.8.dist-info/top_level.txt
physioex-1.0.8.dist-info/RECORD
