Metadata-Version: 2.4
Name: physioex
Version: 1.0.8
Summary: A python package for explainable sleep staging via deep learning
Author-email: Guido Gagliardi <guido.gagliardi@phd.unipi.it>
License: MIT License
Project-URL: Homepage, https://github.com/guidogagl/physioex
Project-URL: Documentation, https://guidogagl.github.io/physioex
Project-URL: Repository, https://github.com/guidogagl/physioex
Project-URL: Issues, https://github.com/guidogagl/physioex/issues
License-File: LICENSE
Requires-Dist: huggingface_hub
Requires-Dist: vector_quantize_pytorch
Requires-Dist: tensorboard
Requires-Dist: boto3
Requires-Dist: botocore
Requires-Dist: braindecode
Requires-Dist: captum
Requires-Dist: dirhash
Requires-Dist: h5py
Requires-Dist: joblib
Requires-Dist: lightning
Requires-Dist: loguru
Requires-Dist: matplotlib
Requires-Dist: npy_append_array
Requires-Dist: numpy
Requires-Dist: pandas
Requires-Dist: paramiko
Requires-Dist: psg_utils
Requires-Dist: pyEDFlib
Requires-Dist: pytorch_lightning
Requires-Dist: pytorch_metric_learning
Requires-Dist: pyunpack
Requires-Dist: PyYAML
Requires-Dist: rarfile
Requires-Dist: requests
Requires-Dist: scikit_learn
Requires-Dist: scipy
Requires-Dist: seaborn
Requires-Dist: setuptools
Requires-Dist: torch
Requires-Dist: torchmetrics
Requires-Dist: tqdm
Requires-Dist: wfdb
Requires-Dist: gdown
Dynamic: license-file
